README.txt
setup.py
test/test.py
toolbox/__init__.py
toolbox/dispatcher.py
toolbox/factory.py
toolbox/handlers.py
toolbox/model.py
toolbox/search.py
toolbox/util.py
toolk0s.egg-info/PKG-INFO
toolk0s.egg-info/SOURCES.txt
toolk0s.egg-info/dependency_links.txt
toolk0s.egg-info/entry_points.txt
toolk0s.egg-info/not-zip-safe
toolk0s.egg-info/requires.txt
toolk0s.egg-info/top_level.txt