Metadata-Version: 1.0
Name: toolk0s
Version: 0.4
Summary: a place to list links + tools
Home-page: http://k0s.org/hg/toolbox/
Author: Jeff Hammel
Author-email: jhammel@mozilla.com
License: MPL
Platform: UNKNOWN
